{
  "Id": "31_38",
  "nombre": "Sector 31_38",
  "bioma": "Campo",
  "Tipo": "Ruta",
  "Descripcion": "Sector autocompletado.",
  "NivelMinimo": 0,
  "NivelMaximo": 0,
  "Enemigos": [],
  "Conexiones": [
    "30_38",
    "31_37",
    "31_39",
    "32_38"
  ],
  "CiudadInicial": false,
  "Eventos": [],
  "Requisitos": {},
  "NodosRecoleccion": [
    {
      "Nombre": "\u00C1rboles de Sauce",
      "Materiales": [],
      "Cooldown": 2,
      "CooldownBase": null,
      "Tipo": null,
      "Requiere": null,
      "Rareza": null,
      "ProduccionMin": 1,
      "ProduccionMax": 2
    },
    {
      "Nombre": "Pradera de Flores",
      "Materiales": [],
      "Cooldown": 1,
      "CooldownBase": null,
      "Tipo": null,
      "Requiere": null,
      "Rareza": null,
      "ProduccionMin": null,
      "ProduccionMax": null
    }
  ],
  "ciudadPrincipal": false,
  "esCentroCiudad": false,
  "parteCiudad": "",
  "Rutas": ""
}